{
    "waves": {
        "wave1": {
            "Altitude [km]": 13.697,
            "Latitude [deg]": -38.9063445,
            "Longitude [deg]": -72.04341125,
            "Date and Time [UTC]": "2020-12-14 06:00:03.250000",
            "Vertical wavelength [km]": 1.088087835171513,
            "Horizontal wavelength [km]": 254.9199116335469,
            "Propagation direction [deg]": 129.6233279870287,
            "Axial ratio [no units]": 1.2146389717196113,
            "Intrinsic vertical group velocity [m/s]": -0.006207613823610037,
            "Intrinsic horizontal group velocity [m/s]": 1.4543351338179575,
            "Intrinsic vertical phase speed [m/s]": 0.019266711626693148,
            "Intrinsic horizontal phase speed [m/s]": 4.513852895498518,
            "Degree of Polarization [no units]": 0.9754991894521038
        },
        "wave2": {
            "Altitude [km]": 22.728,
            "Latitude [deg]": -38.80092500000001,
            "Longitude [deg]": -71.79609450000001,
            "Date and Time [UTC]": "2020-12-14 06:37:26.500000",
            "Vertical wavelength [km]": 1.8903718117931891,
            "Horizontal wavelength [km]": 1378.9202700053897,
            "Propagation direction [deg]": 139.80393815299743,
            "Axial ratio [no units]": 1.0444098495910605,
            "Intrinsic vertical group velocity [m/s]": -0.002390165845331572,
            "Intrinsic horizontal group velocity [m/s]": 1.7434920010132102,
            "Intrinsic vertical phase speed [m/s]": 0.028715916846112625,
            "Intrinsic horizontal phase speed [m/s]": 20.94665163956959,
            "Degree of Polarization [no units]": 0.9736820642294749
        },
        "wave3": {
            "Altitude [km]": 33.458,
            "Latitude [deg]": -38.812080200000004,
            "Longitude [deg]": -72.2921392,
            "Date and Time [UTC]": "2020-12-14 07:15:42.600000",
            "Vertical wavelength [km]": 1.199489078602209,
            "Horizontal wavelength [km]": 201.01202809274864,
            "Propagation direction [deg]": 164.84763523497028,
            "Axial ratio [no units]": 1.3711633861020407,
            "Intrinsic vertical group velocity [m/s]": -0.011200652790782714,
            "Intrinsic horizontal group velocity [m/s]": 1.877020786268118,
            "Intrinsic vertical phase speed [m/s]": 0.02392737973695669,
            "Intrinsic horizontal phase speed [m/s]": 4.00978317658035,
            "Degree of Polarization [no units]": 0.9598951330616724
        },
        "wave4": {
            "Altitude [km]": 27.438,
            "Latitude [deg]": -38.794934,
            "Longitude [deg]": -71.94704949999999,
            "Date and Time [UTC]": "2020-12-14 06:55:36.750000",
            "Vertical wavelength [km]": 0.9764005560913999,
            "Horizontal wavelength [km]": 159.28562048835448,
            "Propagation direction [deg]": -75.55670685702432,
            "Axial ratio [no units]": 1.4098057157894142,
            "Intrinsic vertical group velocity [m/s]": -0.00994664926016596,
            "Intrinsic horizontal group velocity [m/s]": 1.6226518812400768,
            "Intrinsic vertical phase speed [m/s]": 0.020018673504140487,
            "Intrinsic horizontal phase speed [m/s]": 3.265756876691403,
            "Degree of Polarization [no units]": 0.9783640805255316
        },
        "wave5": {
            "Altitude [km]": 34.238,
            "Latitude [deg]": -38.816032,
            "Longitude [deg]": -72.327486,
            "Date and Time [UTC]": "2020-12-14 07:18:08.500000",
            "Vertical wavelength [km]": 0.7693942867763672,
            "Horizontal wavelength [km]": 233.66995732399138,
            "Propagation direction [deg]": 186.99045184443892,
            "Axial ratio [no units]": 2.0016580707921525,
            "Intrinsic vertical group velocity [m/s]": -0.016814604296082798,
            "Intrinsic horizontal group velocity [m/s]": 5.106702682635717,
            "Intrinsic vertical phase speed [m/s]": 0.022407103590166833,
            "Intrinsic horizontal phase speed [m/s]": 6.805180425248464,
            "Degree of Polarization [no units]": 0.9728607993346963
        },
        "wave6": {
            "Altitude [km]": 21.408,
            "Latitude [deg]": -38.81105049999999,
            "Longitude [deg]": -71.78010225,
            "Date and Time [UTC]": "2020-12-14 06:32:15.250000",
            "Vertical wavelength [km]": 0.7611063816705815,
            "Horizontal wavelength [km]": 185.7865383230088,
            "Propagation direction [deg]": -69.4649897028479,
            "Axial ratio [no units]": 1.590085898433162,
            "Intrinsic vertical group velocity [m/s]": -0.010642756200779827,
            "Intrinsic horizontal group velocity [m/s]": 2.597903368539115,
            "Intrinsic vertical phase speed [m/s]": 0.01760621018486347,
            "Intrinsic horizontal phase speed [m/s]": 4.29768679123863,
            "Degree of Polarization [no units]": 0.9583226714398921
        }
    },
    "flightPath": {
        "time": [
            "2020-12-14T05:06:02.000000000",
            "2020-12-14T05:06:35.800000000",
            "2020-12-14T05:07:09.500000000",
            "2020-12-14T05:07:41.600000000",
            "2020-12-14T05:08:15.500000000",
            "2020-12-14T05:08:52.333333000",
            "2020-12-14T05:09:30.500000000",
            "2020-12-14T05:10:08.500000000",
            "2020-12-14T05:10:47.000000000",
            "2020-12-14T05:11:24.500000000",
            "2020-12-14T05:11:58.750000000",
            "2020-12-14T05:12:33.000000000",
            "2020-12-14T05:13:05.000000000",
            "2020-12-14T05:13:36.200000000",
            "2020-12-14T05:14:06.250000000",
            "2020-12-14T05:14:38.500000000",
            "2020-12-14T05:15:12.000000000",
            "2020-12-14T05:15:46.750000000",
            "2020-12-14T05:16:21.500000000",
            "2020-12-14T05:16:55.500000000",
            "2020-12-14T05:17:30.250000000",
            "2020-12-14T05:18:04.500000000",
            "2020-12-14T05:18:37.750000000",
            "2020-12-14T05:19:10.000000000",
            "2020-12-14T05:19:42.250000000",
            "2020-12-14T05:20:16.750000000",
            "2020-12-14T05:20:50.500000000",
            "2020-12-14T05:21:24.750000000",
            "2020-12-14T05:22:02.666667000",
            "2020-12-14T05:22:40.750000000",
            "2020-12-14T05:23:15.250000000",
            "2020-12-14T05:23:50.250000000",
            "2020-12-14T05:24:25.250000000",
            "2020-12-14T05:25:00.666667000",
            "2020-12-14T05:25:39.000000000",
            "2020-12-14T05:26:18.500000000",
            "2020-12-14T05:26:57.666667000",
            "2020-12-14T05:27:48.000000000",
            "2020-12-14T05:28:36.666667000",
            "2020-12-14T05:29:17.666667000",
            "2020-12-14T05:29:59.333333000",
            "2020-12-14T05:30:38.000000000",
            "2020-12-14T05:31:14.750000000",
            "2020-12-14T05:31:48.400000000",
            "2020-12-14T05:32:21.811226000",
            "2020-12-14T05:33:01.642061000",
            "2020-12-14T05:33:41.472895000",
            "2020-12-14T05:34:21.303729000",
            "2020-12-14T05:35:01.134564000",
            "2020-12-14T05:35:40.965398000",
            "2020-12-14T05:36:20.796232000",
            "2020-12-14T05:44:31.000000000",
            "2020-12-14T05:45:20.000000000",
            "2020-12-14T05:46:11.000000000",
            "2020-12-14T05:47:00.666667000",
            "2020-12-14T05:47:47.000000000",
            "2020-12-14T05:48:30.000000000",
            "2020-12-14T05:49:10.000000000",
            "2020-12-14T05:49:47.750000000",
            "2020-12-14T05:50:25.500000000",
            "2020-12-14T05:51:03.666667000",
            "2020-12-14T05:51:42.500000000",
            "2020-12-14T05:52:25.500000000",
            "2020-12-14T05:53:10.000000000",
            "2020-12-14T05:53:53.250000000",
            "2020-12-14T05:54:35.500000000",
            "2020-12-14T05:55:10.600000000",
            "2020-12-14T05:55:42.750000000",
            "2020-12-14T05:56:20.750000000",
            "2020-12-14T05:56:58.250000000",
            "2020-12-14T05:57:32.000000000",
            "2020-12-14T05:58:05.250000000",
            "2020-12-14T05:58:39.800000000",
            "2020-12-14T05:59:17.000000000",
            "2020-12-14T05:59:57.750000000",
            "2020-12-14T06:00:38.333333000",
            "2020-12-14T06:01:19.250000000",
            "2020-12-14T06:02:01.000000000",
            "2020-12-14T06:02:43.500000000",
            "2020-12-14T06:03:26.500000000",
            "2020-12-14T06:04:09.250000000",
            "2020-12-14T06:04:50.250000000",
            "2020-12-14T06:05:28.750000000",
            "2020-12-14T06:06:06.000000000",
            "2020-12-14T06:06:44.750000000",
            "2020-12-14T06:07:24.500000000",
            "2020-12-14T06:08:03.500000000",
            "2020-12-14T06:08:42.250000000",
            "2020-12-14T06:09:22.750000000",
            "2020-12-14T06:10:04.750000000",
            "2020-12-14T06:10:44.750000000",
            "2020-12-14T06:11:25.000000000",
            "2020-12-14T06:12:06.750000000",
            "2020-12-14T06:12:45.800000000",
            "2020-12-14T06:13:14.400000000",
            "2020-12-14T06:13:42.600000000",
            "2020-12-14T06:14:12.000000000",
            "2020-12-14T06:14:45.834829000",
            "2020-12-14T06:15:23.536804000",
            "2020-12-14T06:16:01.238779000",
            "2020-12-14T06:16:38.940754000",
            "2020-12-14T06:17:16.642729000",
            "2020-12-14T06:17:54.344704000",
            "2020-12-14T06:18:32.046679000",
            "2020-12-14T06:19:10.000000000",
            "2020-12-14T06:20:46.000000000",
            "2020-12-14T06:22:15.600000000",
            "2020-12-14T06:23:42.500000000",
            "2020-12-14T06:25:16.750000000",
            "2020-12-14T06:26:50.200000000",
            "2020-12-14T06:28:19.000000000",
            "2020-12-14T06:29:41.750000000",
            "2020-12-14T06:31:13.000000000",
            "2020-12-14T06:32:39.400000000",
            "2020-12-14T06:34:06.250000000",
            "2020-12-14T06:35:33.000000000",
            "2020-12-14T06:37:01.000000000",
            "2020-12-14T06:38:26.500000000",
            "2020-12-14T06:39:55.250000000",
            "2020-12-14T06:41:26.250000000",
            "2020-12-14T06:42:55.000000000",
            "2020-12-14T06:44:22.750000000",
            "2020-12-14T06:45:50.250000000",
            "2020-12-14T06:47:16.200000000",
            "2020-12-14T06:48:45.000000000",
            "2020-12-14T06:50:09.250000000",
            "2020-12-14T06:51:27.000000000",
            "2020-12-14T06:52:47.600000000",
            "2020-12-14T06:54:11.600000000",
            "2020-12-14T06:55:34.500000000",
            "2020-12-14T06:56:55.800000000",
            "2020-12-14T06:58:13.200000000",
            "2020-12-14T06:59:26.000000000",
            "2020-12-14T07:00:39.200000000",
            "2020-12-14T07:01:53.600000000",
            "2020-12-14T07:03:06.000000000",
            "2020-12-14T07:04:17.166667000",
            "2020-12-14T07:05:31.750000000",
            "2020-12-14T07:06:50.400000000",
            "2020-12-14T07:08:09.600000000",
            "2020-12-14T07:09:20.400000000",
            "2020-12-14T07:10:28.000000000",
            "2020-12-14T07:11:35.500000000",
            "2020-12-14T07:12:49.000000000",
            "2020-12-14T07:14:04.800000000",
            "2020-12-14T07:15:20.800000000",
            "2020-12-14T07:16:31.500000000",
            "2020-12-14T07:17:40.833333000",
            "2020-12-14T07:18:50.166667000",
            "2020-12-14T07:19:58.400000000",
            "2020-12-14T07:21:06.000000000",
            "2020-12-14T07:22:22.400000000",
            "2020-12-14T07:23:50.250000000",
            "2020-12-14T07:25:23.750000000"
        ],
        "alt": [
            "1504",
            "1644",
            "1784",
            "1924",
            "2064",
            "2204",
            "2344",
            "2484",
            "2624",
            "2764",
            "2904",
            "3044",
            "3184",
            "3324",
            "3464",
            "3604",
            "3744",
            "3884",
            "4024",
            "4164",
            "4304",
            "4444",
            "4584",
            "4724",
            "4864",
            "5004",
            "5144",
            "5284",
            "5424",
            "5564",
            "5704",
            "5844",
            "5984",
            "6124",
            "6264",
            "6404",
            "6544",
            "6684",
            "6824",
            "6964",
            "7104",
            "7244",
            "7384",
            "7524",
            "7664",
            "7804",
            "7944",
            "8084",
            "8224",
            "8364",
            "8504",
            "10227",
            "10377",
            "10527",
            "10677",
            "10827",
            "10977",
            "11127",
            "11277",
            "11427",
            "11577",
            "11727",
            "11877",
            "12027",
            "12177",
            "12327",
            "12477",
            "12627",
            "12777",
            "12927",
            "13077",
            "13227",
            "13377",
            "13527",
            "13677",
            "13827",
            "13977",
            "14127",
            "14277",
            "14427",
            "14577",
            "14727",
            "14877",
            "15027",
            "15177",
            "15327",
            "15477",
            "15627",
            "15777",
            "15927",
            "16077",
            "16227",
            "16377",
            "16527",
            "16677",
            "16827",
            "16977",
            "17127",
            "17277",
            "17427",
            "17577",
            "17727",
            "17877",
            "18027",
            "18178",
            "18548",
            "18918",
            "19288",
            "19658",
            "20028",
            "20398",
            "20768",
            "21138",
            "21508",
            "21878",
            "22248",
            "22618",
            "22988",
            "23358",
            "23728",
            "24098",
            "24468",
            "24838",
            "25208",
            "25578",
            "25948",
            "26318",
            "26688",
            "27058",
            "27428",
            "27798",
            "28168",
            "28538",
            "28908",
            "29278",
            "29648",
            "30018",
            "30388",
            "30758",
            "31128",
            "31498",
            "31868",
            "32238",
            "32608",
            "32978",
            "33348",
            "33718",
            "34088",
            "34458",
            "34828",
            "35198",
            "35568",
            "35938",
            "36308"
        ]
    }
}