{
    "waves": {
        "wave1": {
            "Altitude [km]": 13.133,
            "Latitude [deg]": -39.0042375,
            "Longitude [deg]": -72.09305749999999,
            "Date and Time [UTC]": "2020-12-14 09:46:33.500000",
            "Vertical wavelength [km]": 7.009419755421262,
            "Horizontal wavelength [km]": 410.866670522936,
            "Propagation direction [deg]": -3.5689284264849492,
            "Axial ratio [no units]": 4.881817962809494,
            "Intrinsic vertical group velocity [m/s]": -0.478918308887155,
            "Intrinsic horizontal group velocity [m/s]": 28.072447918781336,
            "Intrinsic vertical phase speed [m/s]": 0.49989392352452294,
            "Intrinsic horizontal phase speed [m/s]": 29.301962093840128,
            "Degree of Polarization [no units]": 0.9594293534251186
        },
        "wave2": {
            "Altitude [km]": 19.213,
            "Latitude [deg]": -38.921647,
            "Longitude [deg]": -71.85350650000001,
            "Date and Time [UTC]": "2020-12-14 10:06:25.750000",
            "Vertical wavelength [km]": 2.4515089385307016,
            "Horizontal wavelength [km]": 457.13272457154176,
            "Propagation direction [deg]": 218.91564733350026,
            "Axial ratio [no units]": 1.6780700025159048,
            "Intrinsic vertical group velocity [m/s]": -0.03868654735274214,
            "Intrinsic horizontal group velocity [m/s]": 7.213878162004304,
            "Intrinsic vertical phase speed [m/s]": 0.05999066321517601,
            "Intrinsic horizontal phase speed [m/s]": 11.186455367706479,
            "Degree of Polarization [no units]": 0.9093416426924242
        },
        "wave3": {
            "Altitude [km]": 13.573,
            "Latitude [deg]": -38.9977196,
            "Longitude [deg]": -72.0591142,
            "Date and Time [UTC]": "2020-12-14 09:48:03.800000",
            "Vertical wavelength [km]": 1.0196295018737962,
            "Horizontal wavelength [km]": 236.04328613921606,
            "Propagation direction [deg]": -50.723467392281584,
            "Axial ratio [no units]": 1.168513147777957,
            "Intrinsic vertical group velocity [m/s]": -0.004657553379200283,
            "Intrinsic horizontal group velocity [m/s]": 1.0782192972789453,
            "Intrinsic vertical phase speed [m/s]": 0.017403203429529182,
            "Intrinsic horizontal phase speed [m/s]": 4.028825489362701,
            "Degree of Polarization [no units]": 0.9974445020594253
        },
        "wave4": {
            "Altitude [km]": 20.923,
            "Latitude [deg]": -38.904164333333334,
            "Longitude [deg]": -71.846115,
            "Date and Time [UTC]": "2020-12-14 10:12:08.666667",
            "Vertical wavelength [km]": 1.50581550753849,
            "Horizontal wavelength [km]": 355.8816070464731,
            "Propagation direction [deg]": 188.89936998907268,
            "Axial ratio [no units]": 1.42269457650314,
            "Intrinsic vertical group velocity [m/s]": -0.0158001564282603,
            "Intrinsic horizontal group velocity [m/s]": 3.734179275698028,
            "Intrinsic vertical phase speed [m/s]": 0.031229094790263416,
            "Intrinsic horizontal phase speed [m/s]": 7.380625571278031,
            "Degree of Polarization [no units]": 0.9797603280504205
        },
        "wave5": {
            "Altitude [km]": 27.203,
            "Latitude [deg]": -38.88573683333333,
            "Longitude [deg]": -71.98450583333333,
            "Date and Time [UTC]": "2020-12-14 10:31:32.833333",
            "Vertical wavelength [km]": 0.8761774694276577,
            "Horizontal wavelength [km]": 145.33268680543034,
            "Propagation direction [deg]": 127.99854135149026,
            "Axial ratio [no units]": 1.7847189491357613,
            "Intrinsic vertical group velocity [m/s]": -0.015632216996189125,
            "Intrinsic horizontal group velocity [m/s]": 2.592935993053698,
            "Intrinsic vertical phase speed [m/s]": 0.02278582379047908,
            "Intrinsic horizontal phase speed [m/s]": 3.7795139775833264,
            "Degree of Polarization [no units]": 0.9808802441618799
        }
    },
    "flightPath": {
        "time": [
            "2020-12-14T09:05:24.000000000",
            "2020-12-14T09:07:44.500000000",
            "2020-12-14T09:10:02.600000000",
            "2020-12-14T09:12:19.500000000",
            "2020-12-14T09:15:11.000000000",
            "2020-12-14T09:17:28.400000000",
            "2020-12-14T09:19:21.571429000",
            "2020-12-14T09:21:09.500000000",
            "2020-12-14T09:23:27.800000000",
            "2020-12-14T09:25:59.500000000",
            "2020-12-14T09:28:37.200000000",
            "2020-12-14T09:31:21.750000000",
            "2020-12-14T09:33:55.000000000",
            "2020-12-14T09:36:19.600000000",
            "2020-12-14T09:38:34.400000000",
            "2020-12-14T09:40:39.400000000",
            "2020-12-14T09:42:51.800000000",
            "2020-12-14T09:45:15.000000000",
            "2020-12-14T09:47:23.800000000",
            "2020-12-14T09:49:40.800000000",
            "2020-12-14T09:51:47.600000000",
            "2020-12-14T09:53:48.000000000",
            "2020-12-14T09:55:56.200000000",
            "2020-12-14T09:58:00.000000000",
            "2020-12-14T10:00:07.166667000",
            "2020-12-14T10:02:17.600000000",
            "2020-12-14T10:04:32.166667000",
            "2020-12-14T10:06:49.000000000",
            "2020-12-14T10:09:01.200000000",
            "2020-12-14T10:11:14.600000000",
            "2020-12-14T10:13:22.000000000",
            "2020-12-14T10:15:28.166667000",
            "2020-12-14T10:17:32.800000000",
            "2020-12-14T10:19:42.333333000",
            "2020-12-14T10:21:43.400000000",
            "2020-12-14T10:23:51.000000000",
            "2020-12-14T10:25:48.833333000",
            "2020-12-14T10:27:45.800000000",
            "2020-12-14T10:29:46.833333000",
            "2020-12-14T10:31:40.000000000",
            "2020-12-14T10:33:38.333333000",
            "2020-12-14T10:35:24.000000000",
            "2020-12-14T10:37:12.666667000",
            "2020-12-14T10:39:12.833333000",
            "2020-12-14T10:40:56.000000000",
            "2020-12-14T10:42:39.857143000",
            "2020-12-14T10:44:22.714286000",
            "2020-12-14T10:46:03.000000000",
            "2020-12-14T10:47:47.857143000",
            "2020-12-14T10:49:26.571429000",
            "2020-12-14T10:51:11.833333000"
        ],
        "alt": [
            "1503",
            "2163",
            "2823",
            "3483",
            "4143",
            "4803",
            "5463",
            "6123",
            "6783",
            "7443",
            "8103",
            "8763",
            "9423",
            "10083",
            "10743",
            "11403",
            "12063",
            "12723",
            "13383",
            "14043",
            "14703",
            "15363",
            "16023",
            "16683",
            "17343",
            "18003",
            "18663",
            "19323",
            "19983",
            "20643",
            "21303",
            "21963",
            "22623",
            "23283",
            "23943",
            "24603",
            "25263",
            "25923",
            "26583",
            "27243",
            "27903",
            "28563",
            "29223",
            "29883",
            "30543",
            "31203",
            "31863",
            "32523",
            "33183",
            "33843",
            "34503"
        ]
    }
}