{
    "waves": {
        "wave1": {
            "Altitude [km]": 11.599,
            "Latitude [deg]": -38.994265,
            "Longitude [deg]": -72.3784386,
            "Date and Time [UTC]": "2020-12-14 16:08:47.400000",
            "Vertical wavelength [km]": 6.639939156741153,
            "Horizontal wavelength [km]": 486.83441462658016,
            "Propagation direction [deg]": -24.580871332140973,
            "Axial ratio [no units]": 3.064726206831313,
            "Intrinsic vertical group velocity [m/s]": -0.2655749113812636,
            "Intrinsic horizontal group velocity [m/s]": 19.471715548860345,
            "Intrinsic vertical phase speed [m/s]": 0.297219049942751,
            "Intrinsic horizontal phase speed [m/s]": 21.79183555437332,
            "Degree of Polarization [no units]": 0.9224657813893758
        },
        "wave2": {
            "Altitude [km]": 18.709,
            "Latitude [deg]": -38.8802094,
            "Longitude [deg]": -72.03902380000001,
            "Date and Time [UTC]": "2020-12-14 16:30:54.400000",
            "Vertical wavelength [km]": 2.5324697246451384,
            "Horizontal wavelength [km]": 178.9656135452565,
            "Propagation direction [deg]": 23.34850808653483,
            "Axial ratio [no units]": 1.7345159886899708,
            "Intrinsic vertical group velocity [m/s]": -0.042726620038905774,
            "Intrinsic horizontal group velocity [m/s]": 3.01942238265032,
            "Intrinsic vertical phase speed [m/s]": 0.06399903605581278,
            "Intrinsic horizontal phase speed [m/s]": 4.522710239167209,
            "Degree of Polarization [no units]": 0.8981829606690901
        },
        "wave3": {
            "Altitude [km]": 11.109,
            "Latitude [deg]": -39.00987342857143,
            "Longitude [deg]": -72.435497,
            "Date and Time [UTC]": "2020-12-14 16:07:22.714286",
            "Vertical wavelength [km]": 3.1792137600671246,
            "Horizontal wavelength [km]": 98.56688505702829,
            "Propagation direction [deg]": 65.02261924623564,
            "Axial ratio [no units]": 2.531579086174222,
            "Intrinsic vertical group velocity [m/s]": -0.09924383621113017,
            "Intrinsic horizontal group velocity [m/s]": 3.0769103730333858,
            "Intrinsic vertical phase speed [m/s]": 0.1175921086347537,
            "Intrinsic horizontal phase speed [m/s]": 3.64577179458692,
            "Degree of Polarization [no units]": 0.9062764924308436
        },
        "wave4": {
            "Altitude [km]": 12.619,
            "Latitude [deg]": -38.9674034,
            "Longitude [deg]": -72.27215620000001,
            "Date and Time [UTC]": "2020-12-14 16:12:12.200000",
            "Vertical wavelength [km]": 1.2800232559470348,
            "Horizontal wavelength [km]": 302.29164069446716,
            "Propagation direction [deg]": -83.00438053399317,
            "Axial ratio [no units]": 1.3883532847215478,
            "Intrinsic vertical group velocity [m/s]": -0.01248281896958568,
            "Intrinsic horizontal group velocity [m/s]": 2.9479556791460446,
            "Intrinsic vertical phase speed [m/s]": 0.02594102341676611,
            "Intrinsic horizontal phase speed [m/s]": 6.12625942029939,
            "Degree of Polarization [no units]": 0.9978336953445882
        }
    },
    "flightPath": {
        "time": [
            "2020-12-14T15:38:12.000000000",
            "2020-12-14T15:39:47.000000000",
            "2020-12-14T15:41:26.800000000",
            "2020-12-14T15:43:19.800000000",
            "2020-12-14T15:45:08.000000000",
            "2020-12-14T15:46:48.000000000",
            "2020-12-14T15:48:27.500000000",
            "2020-12-14T15:50:11.400000000",
            "2020-12-14T15:51:59.833333000",
            "2020-12-14T15:53:38.333333000",
            "2020-12-14T15:55:18.000000000",
            "2020-12-14T15:56:57.600000000",
            "2020-12-14T15:58:40.000000000",
            "2020-12-14T16:00:17.666667000",
            "2020-12-14T16:01:48.000000000",
            "2020-12-14T16:03:24.800000000",
            "2020-12-14T16:05:12.600000000",
            "2020-12-14T16:06:54.666667000",
            "2020-12-14T16:08:27.600000000",
            "2020-12-14T16:10:14.400000000",
            "2020-12-14T16:12:09.200000000",
            "2020-12-14T16:14:04.200000000",
            "2020-12-14T16:15:57.000000000",
            "2020-12-14T16:17:46.166667000",
            "2020-12-14T16:19:30.800000000",
            "2020-12-14T16:21:19.800000000",
            "2020-12-14T16:23:08.200000000",
            "2020-12-14T16:24:47.500000000",
            "2020-12-14T16:26:16.428571000",
            "2020-12-14T16:27:37.666667000",
            "2020-12-14T16:29:14.000000000",
            "2020-12-14T16:30:54.400000000",
            "2020-12-14T16:32:23.833333000",
            "2020-12-14T16:34:02.833333000",
            "2020-12-14T16:35:44.166667000",
            "2020-12-14T16:37:19.333333000",
            "2020-12-14T16:38:54.000000000",
            "2020-12-14T16:40:28.666667000",
            "2020-12-14T16:42:04.333333000",
            "2020-12-14T16:43:38.166667000",
            "2020-12-14T16:45:08.333333000",
            "2020-12-14T16:46:39.285714000",
            "2020-12-14T16:48:07.500000000",
            "2020-12-14T16:49:32.333333000",
            "2020-12-14T16:50:57.285714000",
            "2020-12-14T16:52:23.500000000",
            "2020-12-14T16:53:46.571429000",
            "2020-12-14T16:55:11.166667000",
            "2020-12-14T16:56:36.000000000",
            "2020-12-14T16:57:57.142857000",
            "2020-12-14T16:59:21.000000000"
        ],
        "alt": [
            "1504",
            "2059",
            "2614",
            "3169",
            "3724",
            "4279",
            "4834",
            "5389",
            "5944",
            "6499",
            "7054",
            "7609",
            "8164",
            "8719",
            "9274",
            "9829",
            "10384",
            "10939",
            "11494",
            "12049",
            "12604",
            "13159",
            "13714",
            "14269",
            "14824",
            "15379",
            "15934",
            "16489",
            "17044",
            "17599",
            "18154",
            "18709",
            "19264",
            "19819",
            "20374",
            "20929",
            "21484",
            "22039",
            "22594",
            "23149",
            "23704",
            "24259",
            "24814",
            "25369",
            "25924",
            "26479",
            "27034",
            "27589",
            "28144",
            "28699",
            "29254"
        ]
    }
}