{
    "waves": {
        "wave1": {
            "Altitude [km]": 20.08,
            "Latitude [deg]": -38.750647,
            "Longitude [deg]": -72.442016,
            "Date and Time [UTC]": "2020-12-14 23:29:28.500000",
            "Amplitude [m2/s2]": 4492.958948714277,
            "Vertical wavelength [km]": 2.176175670343026,
            "Horizontal wavelength [km]": 538.4382484163328,
            "Zonal wavelength [km]": 439.37819277875667,
            "Meridional wavelength [km]": 311.22749086178476,
            "Propagation direction [deg N from E]": 54.68867619633651,
            "Axial ratio [no units]": 1.4002254625420674,
            "Zonal momentum flux [Pa]": -0.0016532450132284034,
            "Meridional momentum flux [Pa]": -0.0005844092321563323,
            "Kinetic energy [m2/s2]": 2.3595761672458675,
            "Potential energy [m2/s2]": 4.906156031262238,
            "Intrinsic vertical group velocity [m/s]": -0.021691162349852453,
            "Intrinsic horizontal group velocity [m/s]": 5.366915741654199,
            "Intrinsic vertical phase speed [m/s]": 0.04427127327510595,
            "Intrinsic horizontal phase speed [m/s]": 10.953778760724509,
            "Degree of Polarization [no units]": 0.9137429635035413
        },
        "wave2": {
            "Altitude [km]": 23.705,
            "Latitude [deg]": -38.72817549999999,
            "Longitude [deg]": -72.472028,
            "Date and Time [UTC]": "2020-12-14 23:38:53.500000",
            "Amplitude [m2/s2]": 3582.6511674703297,
            "Vertical wavelength [km]": 2.673389454165728,
            "Horizontal wavelength [km]": 211.78427426895473,
            "Zonal wavelength [km]": -204.8047554020265,
            "Meridional wavelength [km]": 53.922082603919684,
            "Propagation direction [deg N from E]": -75.24961008035987,
            "Axial ratio [no units]": 3.2581261794295178,
            "Zonal momentum flux [Pa]": -0.0003505357617524313,
            "Meridional momentum flux [Pa]": 0.0007163763491091355,
            "Kinetic energy [m2/s2]": 0.4867289321184868,
            "Potential energy [m2/s2]": 1.6489400282474704,
            "Intrinsic vertical group velocity [m/s]": -0.11457209285919533,
            "Intrinsic horizontal group velocity [m/s]": 9.076330984941402,
            "Intrinsic vertical phase speed [m/s]": 0.12648758855153466,
            "Intrinsic horizontal phase speed [m/s]": 10.020269251707866,
            "Degree of Polarization [no units]": 0.9000026737544272
        },
        "wave3": {
            "Altitude [km]": 28.205,
            "Latitude [deg]": -38.70528528571428,
            "Longitude [deg]": -72.58531542857142,
            "Date and Time [UTC]": "2020-12-14 23:50:31.142857",
            "Amplitude [m2/s2]": 2326.410749249583,
            "Vertical wavelength [km]": 2.0614650783729056,
            "Horizontal wavelength [km]": 601.3761341969949,
            "Zonal wavelength [km]": 564.3039747330195,
            "Meridional wavelength [km]": -207.8804437224383,
            "Propagation direction [deg N from E]": 110.22298018221564,
            "Axial ratio [no units]": 1.2871328762917393,
            "Zonal momentum flux [Pa]": -6.120463186470262e-05,
            "Meridional momentum flux [Pa]": -0.00021736237313251848,
            "Kinetic energy [m2/s2]": 0.5040260521965433,
            "Potential energy [m2/s2]": 2.8599519026308706,
            "Intrinsic vertical group velocity [m/s]": -0.01526610552364306,
            "Intrinsic horizontal group velocity [m/s]": 4.453469340988336,
            "Intrinsic vertical phase speed [m/s]": 0.038512411075359985,
            "Intrinsic horizontal phase speed [m/s]": 11.234944086167026,
            "Degree of Polarization [no units]": 0.9589336266554672
        },
        "wave4": {
            "Altitude [km]": 31.375,
            "Latitude [deg]": -38.68694828571429,
            "Longitude [deg]": -72.69077871428571,
            "Date and Time [UTC]": "2020-12-14 23:58:10.714286",
            "Amplitude [m2/s2]": 1234.1470824130217,
            "Vertical wavelength [km]": 0.7447974413794892,
            "Horizontal wavelength [km]": 95.39237576519122,
            "Zonal wavelength [km]": 28.414414053420558,
            "Meridional wavelength [km]": -91.06221185611635,
            "Propagation direction [deg N from E]": 162.67035583514456,
            "Axial ratio [no units]": 2.2444130098540316,
            "Zonal momentum flux [Pa]": 2.0131200330055696e-05,
            "Meridional momentum flux [Pa]": 4.53308112136807e-06,
            "Kinetic energy [m2/s2]": 0.5773444073982555,
            "Potential energy [m2/s2]": 0.045871882815281095,
            "Intrinsic vertical group velocity [m/s]": -0.019438551707606142,
            "Intrinsic horizontal group velocity [m/s]": 2.489656282100822,
            "Intrinsic vertical phase speed [m/s]": 0.024253185138829268,
            "Intrinsic horizontal phase speed [m/s]": 3.1063062541955526,
            "Degree of Polarization [no units]": 0.9891175867269842
        },
        "wave5": {
            "Altitude [km]": 14.23,
            "Latitude [deg]": -38.83368071428571,
            "Longitude [deg]": -72.58851371428571,
            "Date and Time [UTC]": "2020-12-14 23:13:38.428571",
            "Amplitude [m2/s2]": 826.2371716040162,
            "Vertical wavelength [km]": 0.9554783055979382,
            "Horizontal wavelength [km]": 149.44184702670253,
            "Zonal wavelength [km]": 122.72026343084018,
            "Meridional wavelength [km]": -85.27955549964807,
            "Propagation direction [deg N from E]": 124.7958286949045,
            "Axial ratio [no units]": 1.5612092631360346,
            "Zonal momentum flux [Pa]": 0.0009738751120526204,
            "Meridional momentum flux [Pa]": -0.0005661499613613884,
            "Kinetic energy [m2/s2]": 0.556333085108587,
            "Potential energy [m2/s2]": 0.7815570032765813,
            "Intrinsic vertical group velocity [m/s]": -0.012803912969913652,
            "Intrinsic horizontal group velocity [m/s]": 2.0025995275691977,
            "Intrinsic vertical phase speed [m/s]": 0.021711761403012238,
            "Intrinsic horizontal phase speed [m/s]": 3.395834010316666,
            "Degree of Polarization [no units]": 0.9781968657995392
        },
        "wave6": {
            "Altitude [km]": 27.94,
            "Latitude [deg]": -38.706574,
            "Longitude [deg]": -72.57709557142857,
            "Date and Time [UTC]": "2020-12-14 23:49:52.142857",
            "Amplitude [m2/s2]": 418.0985144556953,
            "Vertical wavelength [km]": 1.1362615992478122,
            "Horizontal wavelength [km]": 338.5759136129864,
            "Zonal wavelength [km]": -120.97903614612646,
            "Meridional wavelength [km]": 316.22416430757266,
            "Propagation direction [deg N from E]": -20.935534231039718,
            "Axial ratio [no units]": 1.2841372779235851,
            "Zonal momentum flux [Pa]": -6.705526284133205e-05,
            "Meridional momentum flux [Pa]": 3.24682183691346e-05,
            "Kinetic energy [m2/s2]": 0.17726224208717184,
            "Potential energy [m2/s2]": 0.5559188747236561,
            "Intrinsic vertical group velocity [m/s]": -0.008335484085078284,
            "Intrinsic horizontal group velocity [m/s]": 2.4837538656416256,
            "Intrinsic vertical phase speed [m/s]": 0.021178895937915606,
            "Intrinsic horizontal phase speed [m/s]": 6.3107510156472895,
            "Degree of Polarization [no units]": 0.9612327597180989
        }
    },
    "flightPath": {
        "time": [
            "2020-12-14T23:03:35.000000000",
            "2020-12-14T23:04:53.666667000",
            "2020-12-14T23:06:17.200000000",
            "2020-12-14T23:07:46.600000000",
            "2020-12-14T23:09:10.666667000",
            "2020-12-14T23:10:39.000000000",
            "2020-12-14T23:12:20.600000000",
            "2020-12-14T23:13:36.857143000",
            "2020-12-14T23:14:55.000000000",
            "2020-12-14T23:16:10.000000000",
            "2020-12-14T23:17:29.000000000",
            "2020-12-14T23:18:48.333333000",
            "2020-12-14T23:20:02.833333000",
            "2020-12-14T23:21:14.166667000",
            "2020-12-14T23:22:27.833333000",
            "2020-12-14T23:23:43.500000000",
            "2020-12-14T23:24:57.714286000",
            "2020-12-14T23:26:08.714286000",
            "2020-12-14T23:27:19.833333000",
            "2020-12-14T23:28:34.000000000",
            "2020-12-14T23:29:46.142857000",
            "2020-12-14T23:30:51.000000000",
            "2020-12-14T23:32:00.833333000",
            "2020-12-14T23:33:14.333333000",
            "2020-12-14T23:34:27.285714000",
            "2020-12-14T23:35:36.857143000",
            "2020-12-14T23:36:47.571429000",
            "2020-12-14T23:38:02.600000000",
            "2020-12-14T23:39:23.666667000",
            "2020-12-14T23:40:37.571429000",
            "2020-12-14T23:41:53.500000000",
            "2020-12-14T23:43:10.500000000",
            "2020-12-14T23:44:25.333333000",
            "2020-12-14T23:45:38.833333000",
            "2020-12-14T23:46:50.500000000",
            "2020-12-14T23:47:56.857143000",
            "2020-12-14T23:49:00.250000000",
            "2020-12-14T23:50:03.571429000",
            "2020-12-14T23:51:13.714286000",
            "2020-12-14T23:52:24.833333000",
            "2020-12-14T23:53:34.000000000",
            "2020-12-14T23:54:39.857143000",
            "2020-12-14T23:55:44.125000000",
            "2020-12-14T23:56:46.142857000",
            "2020-12-14T23:57:51.285714000",
            "2020-12-14T23:58:58.000000000",
            "2020-12-15T00:00:06.000000000",
            "2020-12-15T00:01:12.714286000",
            "2020-12-15T00:02:17.428571000",
            "2020-12-15T00:03:26.571429000",
            "2020-12-15T00:04:37.333333000"
        ],
        "alt": [
            "11000",
            "11460",
            "11920",
            "12380",
            "12840",
            "13300",
            "13760",
            "14220",
            "14680",
            "15140",
            "15600",
            "16060",
            "16520",
            "16980",
            "17440",
            "17900",
            "18360",
            "18820",
            "19280",
            "19740",
            "20200",
            "20660",
            "21120",
            "21580",
            "22040",
            "22500",
            "22960",
            "23420",
            "23880",
            "24340",
            "24800",
            "25260",
            "25720",
            "26180",
            "26640",
            "27100",
            "27560",
            "28020",
            "28480",
            "28940",
            "29400",
            "29860",
            "30320",
            "30780",
            "31240",
            "31700",
            "32160",
            "32620",
            "33080",
            "33540",
            "34000"
        ]
    }
}