{
    "waves": {
        "wave1": {
            "Altitude [km]": 15.407,
            "Latitude [deg]": -38.8629956,
            "Longitude [deg]": -72.5560062,
            "Date and Time [UTC]": "2020-12-13 20:48:36.200000",
            "Vertical wavelength [km]": 5.064939449290277,
            "Horizontal wavelength [km]": 436.85158501757405,
            "Propagation direction [deg]": 54.4233353428252,
            "Axial ratio [no units]": 2.866111211420231,
            "Intrinsic vertical group velocity [m/s]": -0.18568724810598608,
            "Intrinsic horizontal group velocity [m/s]": 16.01554558841136,
            "Intrinsic vertical phase speed [m/s]": 0.21142497660278975,
            "Intrinsic horizontal phase speed [m/s]": 18.235427504305964,
            "Degree of Polarization [no units]": 0.8372088406248935
        },
        "wave2": {
            "Altitude [km]": 12.507,
            "Latitude [deg]": -38.9348314,
            "Longitude [deg]": -72.6718602,
            "Date and Time [UTC]": "2020-12-13 20:39:27.600000",
            "Vertical wavelength [km]": 1.5896068800335623,
            "Horizontal wavelength [km]": 409.88579481546276,
            "Propagation direction [deg]": 220.08145219078122,
            "Axial ratio [no units]": 1.5146240016751762,
            "Intrinsic vertical group velocity [m/s]": -0.019811247728097878,
            "Intrinsic horizontal group velocity [m/s]": 5.108400777144336,
            "Intrinsic vertical phase speed [m/s]": 0.035120315110494245,
            "Intrinsic horizontal phase speed [m/s]": 9.055898319294206,
            "Degree of Polarization [no units]": 0.9611146426107297
        },
        "wave3": {
            "Altitude [km]": 17.267,
            "Latitude [deg]": -38.856888000000005,
            "Longitude [deg]": -72.50101000000001,
            "Date and Time [UTC]": "2020-12-13 20:54:33.800000",
            "Vertical wavelength [km]": 2.8528818932836097,
            "Horizontal wavelength [km]": 770.6682426605769,
            "Propagation direction [deg]": 168.94515400543213,
            "Axial ratio [no units]": 1.4728304062381776,
            "Intrinsic vertical group velocity [m/s]": -0.03298088610534907,
            "Intrinsic horizontal group velocity [m/s]": 8.909349383175194,
            "Intrinsic vertical phase speed [m/s]": 0.061188255804646964,
            "Intrinsic horizontal phase speed [m/s]": 16.529196558557032,
            "Degree of Polarization [no units]": 0.9791103805071818
        },
        "wave4": {
            "Altitude [km]": 12.437,
            "Latitude [deg]": -38.9384894,
            "Longitude [deg]": -72.6753412,
            "Date and Time [UTC]": "2020-12-13 20:39:14.600000",
            "Vertical wavelength [km]": 0.8667392972872472,
            "Horizontal wavelength [km]": 162.6073792162161,
            "Propagation direction [deg]": 146.7215770209287,
            "Axial ratio [no units]": 1.3108888442539874,
            "Intrinsic vertical group velocity [m/s]": -0.0069295489591008255,
            "Intrinsic horizontal group velocity [m/s]": 1.300040045393731,
            "Intrinsic vertical phase speed [m/s]": 0.01657496073741177,
            "Intrinsic horizontal phase speed [m/s]": 3.1095981623975972,
            "Degree of Polarization [no units]": 0.9772908374279179
        },
        "wave5": {
            "Altitude [km]": 23.627,
            "Latitude [deg]": -38.820971,
            "Longitude [deg]": -72.489614,
            "Date and Time [UTC]": "2020-12-13 21:13:00",
            "Vertical wavelength [km]": 1.0307325391864528,
            "Horizontal wavelength [km]": 133.22184242413772,
            "Propagation direction [deg]": 44.66696798614445,
            "Axial ratio [no units]": 1.5889560245439538,
            "Intrinsic vertical group velocity [m/s]": -0.014392460794809834,
            "Intrinsic horizontal group velocity [m/s]": 1.8602208344126918,
            "Intrinsic vertical phase speed [m/s]": 0.023831493976983288,
            "Intrinsic horizontal phase speed [m/s]": 3.080212775507556,
            "Degree of Polarization [no units]": 0.965375065968177
        }
    },
    "flightPath": {
        "time": [
            "2020-12-13T20:05:31.000000000",
            "2020-12-13T20:07:18.166667000",
            "2020-12-13T20:09:04.800000000",
            "2020-12-13T20:10:48.800000000",
            "2020-12-13T20:12:46.000000000",
            "2020-12-13T20:14:44.200000000",
            "2020-12-13T20:16:35.200000000",
            "2020-12-13T20:18:23.800000000",
            "2020-12-13T20:20:12.400000000",
            "2020-12-13T20:21:59.000000000",
            "2020-12-13T20:23:45.166667000",
            "2020-12-13T20:25:26.500000000",
            "2020-12-13T20:27:06.833333000",
            "2020-12-13T20:28:49.833333000",
            "2020-12-13T20:30:33.833333000",
            "2020-12-13T20:32:19.000000000",
            "2020-12-13T20:34:05.000000000",
            "2020-12-13T20:35:55.800000000",
            "2020-12-13T20:37:39.800000000",
            "2020-12-13T20:39:31.200000000",
            "2020-12-13T20:41:15.500000000",
            "2020-12-13T20:43:00.600000000",
            "2020-12-13T20:45:00.000000000",
            "2020-12-13T20:46:49.800000000",
            "2020-12-13T20:48:40.000000000",
            "2020-12-13T20:50:29.500000000",
            "2020-12-13T20:52:16.666667000",
            "2020-12-13T20:54:14.000000000",
            "2020-12-13T20:56:04.833333000",
            "2020-12-13T20:57:53.800000000",
            "2020-12-13T20:59:47.800000000",
            "2020-12-13T21:01:38.000000000",
            "2020-12-13T21:03:14.333333000",
            "2020-12-13T21:04:54.833333000",
            "2020-12-13T21:06:31.833333000",
            "2020-12-13T21:08:04.000000000",
            "2020-12-13T21:09:38.000000000",
            "2020-12-13T21:11:12.833333000",
            "2020-12-13T21:12:47.333333000",
            "2020-12-13T21:14:19.666667000",
            "2020-12-13T21:15:49.714286000",
            "2020-12-13T21:17:18.166667000",
            "2020-12-13T21:18:49.666667000",
            "2020-12-13T21:20:21.666667000",
            "2020-12-13T21:21:49.000000000",
            "2020-12-13T21:23:16.000000000",
            "2020-12-13T21:24:45.833333000",
            "2020-12-13T21:26:17.142857000",
            "2020-12-13T21:27:43.285714000",
            "2020-12-13T21:29:10.714286000",
            "2020-12-13T21:30:35.142857000"
        ],
        "alt": [
            "1507",
            "2087",
            "2667",
            "3247",
            "3827",
            "4407",
            "4987",
            "5567",
            "6147",
            "6727",
            "7307",
            "7887",
            "8467",
            "9047",
            "9627",
            "10207",
            "10787",
            "11367",
            "11947",
            "12527",
            "13107",
            "13687",
            "14267",
            "14847",
            "15427",
            "16007",
            "16587",
            "17167",
            "17747",
            "18327",
            "18907",
            "19487",
            "20067",
            "20647",
            "21227",
            "21807",
            "22387",
            "22967",
            "23547",
            "24127",
            "24707",
            "25287",
            "25867",
            "26447",
            "27027",
            "27607",
            "28187",
            "28767",
            "29347",
            "29927",
            "30507"
        ]
    }
}