{
    "waves": {
        "wave1": {
            "Altitude [km]": 16.545,
            "Latitude [deg]": -38.843577200000006,
            "Longitude [deg]": -71.3851836,
            "Date and Time [UTC]": "2020-12-15 03:30:10.400000",
            "Vertical wavelength [km]": 5.1758471813354845,
            "Horizontal wavelength [km]": 765.6055146226337,
            "Propagation direction [deg]": 182.85112893091772,
            "Axial ratio [no units]": 1.7194368211697046,
            "Intrinsic vertical group velocity [m/s]": -0.08573795784812965,
            "Intrinsic horizontal group velocity [m/s]": 12.682262640543032,
            "Intrinsic vertical phase speed [m/s]": 0.12956089681359828,
            "Intrinsic horizontal phase speed [m/s]": 19.164502661060205,
            "Degree of Polarization [no units]": 0.7762920624365535
        },
        "wave2": {
            "Altitude [km]": 17.11,
            "Latitude [deg]": -38.837794,
            "Longitude [deg]": -71.371892,
            "Date and Time [UTC]": "2020-12-15 03:32:19",
            "Vertical wavelength [km]": 2.9153518721934786,
            "Horizontal wavelength [km]": 111.74927717012204,
            "Propagation direction [deg]": 110.31051233357411,
            "Axial ratio [no units]": 2.800917518534665,
            "Intrinsic vertical group velocity [m/s]": -0.10371098621150282,
            "Intrinsic horizontal group velocity [m/s]": 3.9753787027485052,
            "Intrinsic vertical phase speed [m/s]": 0.11886202799972635,
            "Intrinsic horizontal phase speed [m/s]": 4.556138090442729,
            "Degree of Polarization [no units]": 0.8100898437114622
        },
        "wave3": {
            "Altitude [km]": 12.815,
            "Latitude [deg]": -38.943236999999996,
            "Longitude [deg]": -71.569319,
            "Date and Time [UTC]": "2020-12-15 03:16:20",
            "Vertical wavelength [km]": 2.5324697246451384,
            "Horizontal wavelength [km]": 177.9784281330611,
            "Propagation direction [deg]": -52.04505638495584,
            "Axial ratio [no units]": 3.65120087302872,
            "Intrinsic vertical group velocity [m/s]": -0.12478401403700647,
            "Intrinsic horizontal group velocity [m/s]": 8.769645875056714,
            "Intrinsic vertical phase speed [m/s]": 0.1349033315238212,
            "Intrinsic horizontal phase speed [m/s]": 9.480817346350433,
            "Degree of Polarization [no units]": 0.90582755003957
        },
        "wave4": {
            "Altitude [km]": 21.265,
            "Latitude [deg]": -38.7820694,
            "Longitude [deg]": -71.31288479999999,
            "Date and Time [UTC]": "2020-12-15 03:46:14.800000",
            "Vertical wavelength [km]": 0.9249325209894614,
            "Horizontal wavelength [km]": 83.67410366038354,
            "Propagation direction [deg]": 191.51874941553976,
            "Axial ratio [no units]": 2.123653189272489,
            "Intrinsic vertical group velocity [m/s]": -0.022225330851775922,
            "Intrinsic horizontal group velocity [m/s]": 2.010616553506402,
            "Intrinsic vertical phase speed [m/s]": 0.028557509172851502,
            "Intrinsic horizontal phase speed [m/s]": 2.583457634569167,
            "Degree of Polarization [no units]": 0.8519732761535815
        },
        "wave5": {
            "Altitude [km]": 11.275,
            "Latitude [deg]": -38.993919,
            "Longitude [deg]": -71.677115,
            "Date and Time [UTC]": "2020-12-15 03:10:27",
            "Vertical wavelength [km]": 1.4576759360967393,
            "Horizontal wavelength [km]": 132.1487972438338,
            "Propagation direction [deg]": 70.80244426558608,
            "Axial ratio [no units]": 2.4300719864932603,
            "Intrinsic vertical group velocity [m/s]": -0.04297546650540223,
            "Intrinsic horizontal group velocity [m/s]": 3.8960348243717386,
            "Intrinsic vertical phase speed [m/s]": 0.05173658321423355,
            "Intrinsic horizontal phase speed [m/s]": 4.690293004063661,
            "Degree of Polarization [no units]": 0.9350170675180707
        }
    },
    "flightPath": {
        "time": [
            [
                "2020-12-15 02:36:58"
            ],
            [
                "2020-12-15 02:38:58.200000"
            ],
            [
                "2020-12-15 02:40:58.600000"
            ],
            [
                "2020-12-15 02:43:02.400000"
            ],
            [
                "2020-12-15 02:45:04.600000"
            ],
            [
                "2020-12-15 02:47:14.800000"
            ],
            [
                "2020-12-15 02:49:34.250000"
            ],
            [
                "2020-12-15 02:51:43.400000"
            ],
            [
                "2020-12-15 02:53:57.800000"
            ],
            [
                "2020-12-15 02:56:03.600000"
            ],
            [
                "2020-12-15 02:58:06.800000"
            ],
            [
                "2020-12-15 03:00:25.250000"
            ],
            [
                "2020-12-15 03:02:48.600000"
            ],
            [
                "2020-12-15 03:05:09"
            ],
            [
                "2020-12-15 03:07:26.750000"
            ],
            [
                "2020-12-15 03:09:59.250000"
            ],
            [
                "2020-12-15 03:12:25.200000"
            ],
            [
                "2020-12-15 03:14:48.750000"
            ],
            [
                "2020-12-15 03:17:06.600000"
            ],
            [
                "2020-12-15 03:19:23.800000"
            ],
            [
                "2020-12-15 03:21:42.200000"
            ],
            [
                "2020-12-15 03:24:15.600000"
            ],
            [
                "2020-12-15 03:26:30"
            ],
            [
                "2020-12-15 03:28:42.800000"
            ],
            [
                "2020-12-15 03:31:05.800000"
            ],
            [
                "2020-12-15 03:33:15.833333"
            ],
            [
                "2020-12-15 03:35:20.750000"
            ],
            [
                "2020-12-15 03:38:05"
            ],
            [
                "2020-12-15 03:40:03.069074"
            ],
            [
                "2020-12-15 03:41:58.846154"
            ],
            [
                "2020-12-15 03:43:54"
            ],
            [
                "2020-12-15 03:45:52.400000"
            ],
            [
                "2020-12-15 03:48:00.600000"
            ],
            [
                "2020-12-15 03:49:56.284631"
            ],
            [
                "2020-12-15 03:51:51.291523"
            ],
            [
                "2020-12-15 03:53:45.166667"
            ],
            [
                "2020-12-15 03:55:31.400000"
            ],
            [
                "2020-12-15 03:57:26.800000"
            ],
            [
                "2020-12-15 03:59:17.833333"
            ],
            [
                "2020-12-15 04:01:05.166667"
            ],
            [
                "2020-12-15 04:02:55.666667"
            ],
            [
                "2020-12-15 04:04:38.333333"
            ],
            [
                "2020-12-15 04:06:27.800000"
            ],
            [
                "2020-12-15 04:08:11.833333"
            ],
            [
                "2020-12-15 04:09:51.166667"
            ],
            [
                "2020-12-15 04:11:34"
            ],
            [
                "2020-12-15 04:13:10.571429"
            ],
            [
                "2020-12-15 04:14:45.666667"
            ],
            [
                "2020-12-15 04:16:30.666667"
            ],
            [
                "2020-12-15 04:18:08.333333"
            ],
            [
                "2020-12-15 04:19:51.800000"
            ]
        ],
        "alt": [
            [
                1780
            ],
            [
                2405
            ],
            [
                3030
            ],
            [
                3655
            ],
            [
                4280
            ],
            [
                4905
            ],
            [
                5530
            ],
            [
                6155
            ],
            [
                6780
            ],
            [
                7405
            ],
            [
                8030
            ],
            [
                8655
            ],
            [
                9280
            ],
            [
                9905
            ],
            [
                10530
            ],
            [
                11155
            ],
            [
                11780
            ],
            [
                12405
            ],
            [
                13030
            ],
            [
                13655
            ],
            [
                14280
            ],
            [
                14905
            ],
            [
                15530
            ],
            [
                16155
            ],
            [
                16780
            ],
            [
                17405
            ],
            [
                18030
            ],
            [
                18655
            ],
            [
                19280
            ],
            [
                19905
            ],
            [
                20530
            ],
            [
                21155
            ],
            [
                21780
            ],
            [
                22405
            ],
            [
                23030
            ],
            [
                23655
            ],
            [
                24280
            ],
            [
                24905
            ],
            [
                25530
            ],
            [
                26155
            ],
            [
                26780
            ],
            [
                27405
            ],
            [
                28030
            ],
            [
                28655
            ],
            [
                29280
            ],
            [
                29905
            ],
            [
                30530
            ],
            [
                31155
            ],
            [
                31780
            ],
            [
                32405
            ],
            [
                33030
            ]
        ]
    }
}